{
  "url": "https://www.upwork.com/jobs/~022070493442751705197",
  "title": "Senior Python Backend Engineer (AWS Asset & Portfolio Mgmt Platform)",
  "budget": "$30-50/hr",
  "tier": "EXPERT",
  "client": "(via Upwork)",
  "duration": "3-6 months",
  "hours": ">30 hrs/week",
  "skills": [
    "Python",
    "AWS Lambda",
    "Amazon DynamoDB",
    "Amazon S3",
    "AWS Cognito",
    "API Development",
    "Data Parsing",
    "ETL Pipelines",
    "REST API",
    "Serverless"
  ],
  "description": "Cloud-based asset and portfolio management platform integrating financial reporting, property management systems, and workflow automation. AWS backend (Cognito/IAM, Lambda, S3, DynamoDB), FastAPI/Flask REST API, ETL pipelines for lender/bank + property manager reports (Yardi, Excel), Monday.com integration. Implementing services on defined architecture. >30 hrs/week, 3-6 months.",
  "state": "BUILDING",
  "priority": 1,
  "tech_stack": [
    "Python",
    "AWS Lambda",
    "Amazon DynamoDB",
    "Amazon S3",
    "AWS Cognito",
    "API Development",
    "Data Parsing",
    "ETL Pipelines",
    "REST API",
    "Serverless"
  ],
  "job_id": "JOB-20260626153537-000112",
  "created_at": "2026-06-26T15:35:37.373032+00:00",
  "cto_approved": true,
  "_version": 9,
  "retry_count": 0,
  "history": [],
  "build_issue_id": null,
  "confidence": 0.0,
  "tags": [],
  "full_description": "Cloud-based asset and portfolio management platform integrating financial reporting, property management systems, and workflow automation. AWS backend (Cognito/IAM, Lambda, S3, DynamoDB), FastAPI/Flask REST API, ETL pipelines for lender/bank + property manager reports (Yardi, Excel), Monday.com integration. Implementing services on defined architecture. >30 hrs/week, 3-6 months.",
  "lead_url": "",
  "notified_ceo_intake_at": "2026-06-26T17:45:34.703626",
  "ceo_review_issue_id": "f432c1dc-faf8-45f7-acfb-05e287872c75",
  "github_url": "https://github.com/9KMan/JOB-20260626153537-000112",
  "updated_at": "2026-06-26T15:59:56.715394+00:00",
  "ceo_verdict": {
    "verdict": "a",
    "label": "APPROVED",
    "confidence": "high",
    "stored_at": "2026-06-26T16:02:50.021565+00:00"
  },
  "assignee": null,
  "assigned_at": null,
  "cto_approved_at": "2026-06-26T16:03:49.328794+00:00"
}